{
  "generated_at": "2026-06-24T16:23:12.721015+00:00",
  "status": "ok",
  "scanners": {
    "stablecoin_pegs": {
      "all_stablecoins": [
        {
          "symbol": "USDT",
          "coin_id": "tether",
          "price": 0.998575,
          "deviation_from_peg": 0.001425,
          "deviation_pct": 0.1425,
          "direction": "below",
          "change_24h": -0.02081891138595031,
          "volume_24h": 46186480900.57807,
          "is_opportunity": false
        },
        {
          "symbol": "USDC",
          "coin_id": "usd-coin",
          "price": 0.999754,
          "deviation_from_peg": 0.000246,
          "deviation_pct": 0.0246,
          "direction": "below",
          "change_24h": 0.0027191855176303976,
          "volume_24h": 11019838932.465157,
          "is_opportunity": false
        },
        {
          "symbol": "DAI",
          "coin_id": "dai",
          "price": 0.999765,
          "deviation_from_peg": 0.000235,
          "deviation_pct": 0.0235,
          "direction": "below",
          "change_24h": -0.0015107489385420923,
          "volume_24h": 150537154.9393706,
          "is_opportunity": false
        },
        {
          "symbol": "TUSD",
          "coin_id": "true-usd",
          "price": 0.998235,
          "deviation_from_peg": 0.001765,
          "deviation_pct": 0.1765,
          "direction": "below",
          "change_24h": -0.038202090377939424,
          "volume_24h": 15789511.44309675,
          "is_opportunity": false
        },
        {
          "symbol": "FRAX",
          "coin_id": "frax",
          "price": 0.988944,
          "deviation_from_peg": 0.011056,
          "deviation_pct": 1.1056,
          "direction": "below",
          "change_24h": -0.1266292892248062,
          "volume_24h": 224237.107237584,
          "is_opportunity": true,
          "action": "Buy FRAX at $0.9889, redeem at $1.00",
          "profit_per_unit": 0.011056
        },
        {
          "symbol": "USDT/USDC",
          "coin_id": "cross-stable",
          "price": null,
          "deviation_from_peg": 0.001179,
          "deviation_pct": 0.1179,
          "direction": "spread",
          "change_24h": 0,
          "volume_24h": 0,
          "is_opportunity": false,
          "action": "Buy USDT -> swap to USDC (spread: $0.0012)",
          "profit_per_unit": 0.001179
        }
      ],
      "opportunities": [
        {
          "symbol": "FRAX",
          "coin_id": "frax",
          "price": 0.988944,
          "deviation_from_peg": 0.011056,
          "deviation_pct": 1.1056,
          "direction": "below",
          "change_24h": -0.1266292892248062,
          "volume_24h": 224237.107237584,
          "is_opportunity": true,
          "action": "Buy FRAX at $0.9889, redeem at $1.00",
          "profit_per_unit": 0.011056
        }
      ],
      "count": 1
    },
    "crypto_spreads": {
      "opportunities": [],
      "count": 0,
      "coins_checked": 5
    },
    "kalshi_mispricings": {
      "opportunities": [],
      "count": 0,
      "series_checked": 8
    }
  },
  "summary": {
    "total_opportunities": 1,
    "stablecoin_peg_opps": 1,
    "crypto_spread_opps": 0,
    "kalshi_mispricing_opps": 0,
    "best_opportunity": {
      "type": "stablecoin_peg",
      "detail": {
        "symbol": "FRAX",
        "coin_id": "frax",
        "price": 0.988944,
        "deviation_from_peg": 0.011056,
        "deviation_pct": 1.1056,
        "direction": "below",
        "change_24h": -0.1266292892248062,
        "volume_24h": 224237.107237584,
        "is_opportunity": true,
        "action": "Buy FRAX at $0.9889, redeem at $1.00",
        "profit_per_unit": 0.011056
      }
    },
    "scan_time": "2026-06-24T16:23:19.196726+00:00"
  },
  "elapsed_seconds": 6.5
}
